{"frameRate":24,"isGlobal":0,"name":"NewProject-loading01","version":"5.5","armature":[{"slot":[{"displayIndex":37,"name":"sheetSlot","parent":"root","color":{}}],"bone":[{"name":"root","transform":{}}],"aabb":{"width":1080,"y":-960,"height":1920,"x":-540},"skin":[{"slot":[{"display":[{"path":"bg_00000","type":"image","name":"bg_00000","transform":{}},{"path":"bg_00001","type":"image","name":"bg_00001","transform":{}},{"path":"bg_00002","type":"image","name":"bg_00002","transform":{}},{"path":"bg_00003","type":"image","name":"bg_00003","transform":{}},{"path":"bg_00004","type":"image","name":"bg_00004","transform":{}},{"path":"bg_00005","type":"image","name":"bg_00005","transform":{}},{"path":"bg_00006","type":"image","name":"bg_00006","transform":{}},{"path":"bg_00007","type":"image","name":"bg_00007","transform":{}},{"path":"bg_00008","type":"image","name":"bg_00008","transform":{}},{"path":"bg_00009","type":"image","name":"bg_00009","transform":{}},{"path":"bg_00010","type":"image","name":"bg_00010","transform":{}},{"path":"bg_00011","type":"image","name":"bg_00011","transform":{}},{"path":"bg_00012","type":"image","name":"bg_00012","transform":{}},{"path":"bg_00013","type":"image","name":"bg_00013","transform":{}},{"path":"bg_00014","type":"image","name":"bg_00014","transform":{}},{"path":"bg_00015","type":"image","name":"bg_00015","transform":{}},{"path":"bg_00016","type":"image","name":"bg_00016","transform":{}},{"path":"bg_00017","type":"image","name":"bg_00017","transform":{}},{"path":"bg_00018","type":"image","name":"bg_00018","transform":{}},{"path":"bg_00019","type":"image","name":"bg_00019","transform":{}},{"path":"bg_00020","type":"image","name":"bg_00020","transform":{}},{"path":"bg_00021","type":"image","name":"bg_00021","transform":{}},{"path":"bg_00022","type":"image","name":"bg_00022","transform":{}},{"path":"bg_00023","type":"image","name":"bg_00023","transform":{}},{"path":"bg_00024","type":"image","name":"bg_00024","transform":{}},{"path":"bg_00025","type":"image","name":"bg_00025","transform":{}},{"path":"bg_00026","type":"image","name":"bg_00026","transform":{}},{"path":"bg_00027","type":"image","name":"bg_00027","transform":{}},{"path":"bg_00028","type":"image","name":"bg_00028","transform":{}},{"path":"bg_00029","type":"image","name":"bg_00029","transform":{}},{"path":"bg_00030","type":"image","name":"bg_00030","transform":{}},{"path":"bg_00031","type":"image","name":"bg_00031","transform":{}},{"path":"bg_00032","type":"image","name":"bg_00032","transform":{}},{"path":"bg_00033","type":"image","name":"bg_00033","transform":{}},{"path":"bg_00034","type":"image","name":"bg_00034","transform":{}},{"path":"bg_00035","type":"image","name":"bg_00035","transform":{}},{"path":"bg_00036","type":"image","name":"bg_00036","transform":{}},{"path":"bg_00037","type":"image","name":"bg_00037","transform":{}},{"path":"bg_00000","type":"image","name":"bg_1","transform":{}},{"path":"bg_00001","type":"image","name":"bg_2","transform":{}},{"path":"bg_00002","type":"image","name":"bg_3","transform":{}},{"path":"bg_00003","type":"image","name":"bg_4","transform":{}},{"path":"bg_00004","type":"image","name":"bg_5","transform":{}},{"path":"bg_00005","type":"image","name":"bg_6","transform":{}},{"path":"bg_00006","type":"image","name":"bg_7","transform":{}},{"path":"bg_00007","type":"image","name":"bg_8","transform":{}},{"path":"bg_00008","type":"image","name":"bg_9","transform":{}},{"path":"bg_00009","type":"image","name":"bg_10","transform":{}},{"path":"bg_00010","type":"image","name":"bg_11","transform":{}},{"path":"bg_00011","type":"image","name":"bg_12","transform":{}},{"path":"bg_00012","type":"image","name":"bg_13","transform":{}},{"path":"bg_00013","type":"image","name":"bg_14","transform":{}},{"path":"bg_00014","type":"image","name":"bg_15","transform":{}},{"path":"bg_00015","type":"image","name":"bg_16","transform":{}},{"path":"bg_00016","type":"image","name":"bg_17","transform":{}},{"path":"bg_00017","type":"image","name":"bg_18","transform":{}},{"path":"bg_00018","type":"image","name":"bg_19","transform":{}},{"path":"bg_00019","type":"image","name":"bg_20","transform":{}},{"path":"bg_00020","type":"image","name":"bg_21","transform":{}},{"path":"bg_00021","type":"image","name":"bg_22","transform":{}},{"path":"bg_00022","type":"image","name":"bg_23","transform":{}},{"path":"bg_00023","type":"image","name":"bg_24","transform":{}},{"path":"bg_00024","type":"image","name":"bg_25","transform":{}},{"path":"bg_00025","type":"image","name":"bg_26","transform":{}},{"path":"bg_00026","type":"image","name":"bg_27","transform":{}},{"path":"bg_00027","type":"image","name":"bg_28","transform":{}},{"path":"bg_00028","type":"image","name":"bg_29","transform":{}},{"path":"bg_00029","type":"image","name":"bg_30","transform":{}},{"path":"bg_00030","type":"image","name":"bg_31","transform":{}},{"path":"bg_00031","type":"image","name":"bg_32","transform":{}},{"path":"bg_00032","type":"image","name":"bg_33","transform":{}},{"path":"bg_00033","type":"image","name":"bg_34","transform":{}},{"path":"bg_00034","type":"image","name":"bg_35","transform":{}},{"path":"bg_00035","type":"image","name":"bg_36","transform":{}},{"path":"bg_00036","type":"image","name":"bg_37","transform":{}},{"path":"bg_00037","type":"image","name":"bg_38","transform":{}}],"name":"sheetSlot"}],"name":""}],"type":"Sheet","frameRate":24,"animation":[{"bone":[],"frame":[],"duration":76,"slot":[{"displayFrame":[{"duration":1},{"value":1,"duration":1},{"value":2,"duration":1},{"value":3,"duration":1},{"value":4,"duration":1},{"value":5,"duration":1},{"value":6,"duration":1},{"value":7,"duration":1},{"value":8,"duration":1},{"value":9,"duration":1},{"value":10,"duration":1},{"value":11,"duration":1},{"value":12,"duration":1},{"value":13,"duration":1},{"value":14,"duration":1},{"value":15,"duration":1},{"value":16,"duration":1},{"value":17,"duration":1},{"value":18,"duration":1},{"value":19,"duration":1},{"value":20,"duration":1},{"value":21,"duration":1},{"value":22,"duration":1},{"value":23,"duration":1},{"value":24,"duration":1},{"value":25,"duration":1},{"value":26,"duration":1},{"value":27,"duration":1},{"value":28,"duration":1},{"value":29,"duration":1},{"value":30,"duration":1},{"value":31,"duration":1},{"value":32,"duration":1},{"value":33,"duration":1},{"value":34,"duration":1},{"value":35,"duration":1},{"value":36,"duration":1},{"value":37,"duration":1},{"value":38,"duration":1},{"value":39,"duration":1},{"value":40,"duration":1},{"value":41,"duration":1},{"value":42,"duration":1},{"value":43,"duration":1},{"value":44,"duration":1},{"value":45,"duration":1},{"value":46,"duration":1},{"value":47,"duration":1},{"value":48,"duration":1},{"value":49,"duration":1},{"value":50,"duration":1},{"value":51,"duration":1},{"value":52,"duration":1},{"value":53,"duration":1},{"value":54,"duration":1},{"value":55,"duration":1},{"value":56,"duration":1},{"value":57,"duration":1},{"value":58,"duration":1},{"value":59,"duration":1},{"value":60,"duration":1},{"value":61,"duration":1},{"value":62,"duration":1},{"value":63,"duration":1},{"value":64,"duration":1},{"value":65,"duration":1},{"value":66,"duration":1},{"value":67,"duration":1},{"value":68,"duration":1},{"value":69,"duration":1},{"value":70,"duration":1},{"value":71,"duration":1},{"value":72,"duration":1},{"value":73,"duration":1},{"value":74,"duration":1},{"value":75,"duration":1}],"colorFrame":[],"name":"sheetSlot"}],"playTimes":0,"ik":[],"ffd":[],"name":"Sprite"}],"defaultActions":[{"gotoAndPlay":"Sprite"}],"ik":[],"name":"Sprite"}]}